mu2/__init__.py
mu2/bind.py
mu2/counterterm.py
mu2/interaction.py
mu2/scatter.py
mu2/system.py
mu2/utility.py
mu2/cc/cscatter.py
mu2/cc/test.py
mu2-1.6.dist-info/LICENSE
mu2-1.6.dist-info/METADATA
mu2-1.6.dist-info/WHEEL
mu2-1.6.dist-info/top_level.txt
mu2-1.6.dist-info/RECORD
