Metadata-Version: 2.1
Name: mu2
Version: 1.6
Summary: Two-body scattering and bound-state codes.
Author-email: Daniel Odell <dodell@ohio.edo>
License: Copyright (c) 2018 The Python Packaging Authority
Classifier: Programming Language :: Python :: 3
Classifier: License :: OSI Approved :: MIT License
Classifier: Operating System :: OS Independent
Requires-Python: >=3.10
License-File: LICENSE
